lumineer/__init__.py
lumineer/flashcards/__init__.py
lumineer/flashcards/__main__.py
lumineer/flashcards/main.py
lumineer/scholyr/.DS_Store
lumineer/scholyr/Scholyr.sh
lumineer/scholyr/__init__.py
lumineer/scholyr/__main__.py
lumineer/scholyr/gradebooks/Biology Seminar.json
lumineer/scholyr/gradebooks/CRISPR-Based Gene Therapy.json
lumineer/scholyr/gradebooks/Cellular and Molecular Biology (Lab).json
lumineer/scholyr/gradebooks/Cellular and Molecular Biology (Lecture).json
lumineer/scholyr/gradebooks/Cellular and Molecular Biology.json
lumineer/scholyr/gradebooks/Course Title.json
lumineer/scholyr/gradebooks/Developmental Biology.json
lumineer/scholyr/gradebooks/Developmental Biology_SP24.json
lumineer/scholyr/gradebooks/Introduction to Biochemistry.json
lumineer/scholyr/gradebooks/Introduction to Physics II.json
lumineer/scholyr/gradebooks/Introduction to Physics II_SP24.json
lumineer/scholyr/gradebooks/Microscale Organic Chemistry Lab.json
lumineer/scholyr/gradebooks/Microscale Organic Chemistry.json
lumineer/scholyr/gradebooks/Microscale Organic Chemistry_SP24.json
lumineer/scholyr/gradebooks/Organic Chemistry II.json
lumineer/scholyr/gradebooks/Organic Chemistry II_SP24.json
lumineer/scholyr/gradebooks/Organic Chemistry II_SU24.json
lumineer/scholyr/gradebooks/Statistical Methods for Biologists.json
lumineer/scholyr/gradebooks/Statistical Methods for Biologists_SP24.json
lumineer/scholyr/gradebooks/Title.json
lumineer/scholyr/main.egg-info/PKG-INFO
lumineer/scholyr/main.egg-info/SOURCES.txt
lumineer/scholyr/main.egg-info/dependency_links.txt
lumineer/scholyr/main.egg-info/top_level.txt
lumineer/scholyr/main.py
lumineer/scholyr/record.json
lumineer/scholyr/schedule.json
lumineer/scholyr/scholyr_pythonista.py
lumineer/scholyr/scholyr_pythonista_ui.pyui
lumineer/scholyr/setup.py
lumineer-0.0.0.dist-info/METADATA
lumineer-0.0.0.dist-info/WHEEL
lumineer-0.0.0.dist-info/entry_points.txt
lumineer-0.0.0.dist-info/RECORD
