Metadata-Version: 2.1
Name: lumineer
Version: 0.0.0
Summary: School tools
License: Apache-2.0
Author: K. LeBryce
Author-email: kosmolebryce@pm.me
Requires-Python: >=3.12,<4.0
Classifier: License :: OSI Approved :: Apache Software License
Classifier: Programming Language :: Python :: 3
Classifier: Programming Language :: Python :: 3.12
Requires-Dist: appdirs (>=1.4.4,<2.0.0)
Requires-Dist: markdown (>=3.6,<4.0)
Requires-Dist: pyqt5 (>=5.15.11,<6.0.0)
